analysisbykwok/__init__.py
analysisbykwok/_version.py
analysisbykwok-0.0.29.dist-info/METADATA
analysisbykwok-0.0.29.dist-info/WHEEL
analysisbykwok-0.0.29.dist-info/top_level.txt
analysisbykwok-0.0.29.dist-info/RECORD
