Metadata-Version: 2.1
Name: analysisbykwok
Version: 0.0.29
Requires-Dist: pandas
Requires-Dist: requests
Requires-Dist: pyexecjs
Requires-Dist: tushare
Requires-Dist: openpyxl
